[
  {
  "UserName": "sacd",
  "Address": "cds",
  "Perfil": "ADMIN",
  "FirstName": "sdc",
  "PhoneNumber": "asdc",
  "ID": 1,
  "LastName": "sadvc",
  "PassWord": "acsd",
  "Name": "JUAN"
},
{
  "UserName": "sacd",
  "Address": "cds",
  "Perfil": "ADMIN",
  "FirstName": "sdc",
  "PhoneNumber": "asdc",
  "ID": 2,
  "LastName": "sadvc",
  "PassWord": "acsd",
  "Name": "PEDRO"
},
{
  "UserName": "sacd",
  "Address": "cds",
  "Perfil": "ADMIN",
  "FirstName": "sdc",
  "PhoneNumber": "asdc",
  "ID": 3,
  "LastName": "sadvc",
  "PassWord": "acsd",
  "Name": "FRANCISCO"
},
{
  "UserName": "sacd",
  "Address": "cds",
  "Perfil": "ADMIN",
  "FirstName": "sdc",
  "PhoneNumber": "asdc",
  "ID": 4,
  "LastName": "sadvc",
  "PassWord": "acsd",
  "Name": "TONIO"
},
{
  "UserName": "sacd",
  "Address": "cds",
  "Perfil": "ADMIN",
  "FirstName": "sdc",
  "PhoneNumber": "asdc",
  "ID": 6,
  "LastName": "sadvc",
  "PassWord": "acsd",
  "Name": "TUMAMA"
},
{
  "UserName": "sacd",
  "Address": "cds",
  "Perfil": "ADMIN",
  "FirstName": "sdc",
  "PhoneNumber": "asdc",
  "ID": 7,
  "LastName": "sadvc",
  "PassWord": "acsd",
  "Name": "BENITO"
},
{
  "UserName": "sacd",
  "Address": "cds",
  "Perfil": "ADMIN",
  "FirstName": "sdc",
  "PhoneNumber": "asdc",
  "ID": 8,
  "LastName": "sadvc",
  "PassWord": "acsd",
  "Name": "JOSEJUAN"
},
{
  "UserName": "sacd",
  "Address": "cds",
  "Perfil": "ADMIN",
  "FirstName": "sdc",
  "PhoneNumber": "asdc",
  "ID": 9,
  "LastName": "sadvc",
  "PassWord": "acsd",
  "Name": "PONCHO"
},
{
  "UserName": "sacd",
  "Address": "cds",
  "Perfil": "ADMIN",
  "FirstName": "sdc",
  "PhoneNumber": "asdc",
  "ID": 10,
  "LastName": "sadvc",
  "PassWord": "acsd",
  "Name": "OSCAR"
},
{
  "UserName": "sacd",
  "Address": "cds",
  "Perfil": "ADMIN",
  "FirstName": "sdc",
  "PhoneNumber": "asdc",
  "ID": 11,
  "LastName": "sadvc",
  "PassWord": "acsd",
  "Name": "FRANCO"
}
]